[
  {
    "id": 1764353341246,
    "name": "yug",
    "phone": "7869145276",
    "items": [
      {
        "id": 10,
        "title": "Math Puzzles Club",
        "quantity": 4,
        "price": 12
      },
      {
        "id": 3,
        "title": "Drama & Theatre",
        "quantity": 2,
        "price": 22
      }
    ],
    "total": 92,
    "createdAt": "2025-11-28T18:09:01.246Z"
  },
  {
    "id": 1764354466994,
    "name": "yug",
    "phone": "1324545666",
    "items": [
      {
        "id": 9,
        "title": "Creative Writing",
        "quantity": 5,
        "price": 15
      },
      {
        "id": 4,
        "title": "Coding for Kids",
        "quantity": 3,
        "price": 28
      }
    ],
    "total": 159,
    "createdAt": "2025-11-28T18:27:46.994Z"
  }
]